README.md
setup.py
elle/sections/__init__.py
elle/sections/core.py
elle/sections/core_v2.py
elle/sections/postprocessing.py
elle/sections/simple.py
elle/sections/utils.py
elle_sections.egg-info/PKG-INFO
elle_sections.egg-info/SOURCES.txt
elle_sections.egg-info/dependency_links.txt
elle_sections.egg-info/namespace_packages.txt
elle_sections.egg-info/top_level.txt