Metadata-Version: 1.1
Name: elle-sections
Version: 0.0.0
Summary: UNKNOWN
Home-page: https://github.com/claudioperez/elle-sections
Author: Claudio Perez
Author-email: claudio_perez@berkeley.edu
License: UNKNOWN
Platform: UNKNOWN
Classifier: Development Status :: 2 - Pre-Alpha
Classifier: Programming Language :: Python :: 3
